GoogleTrans2020/CalcTk.py
GoogleTrans2020/Translator.py
GoogleTrans2020/__init__.py
GoogleTrans2020/common.py
GoogleTrans2020/gettkk.py
GoogleTrans2020/terminal.py
GoogleTrans2020-4.0.2020.2.dist-info/LICENSE
GoogleTrans2020-4.0.2020.2.dist-info/METADATA
GoogleTrans2020-4.0.2020.2.dist-info/WHEEL
GoogleTrans2020-4.0.2020.2.dist-info/entry_points.txt
GoogleTrans2020-4.0.2020.2.dist-info/top_level.txt
GoogleTrans2020-4.0.2020.2.dist-info/RECORD
